Hastebin/Hastebin.py
Hastebin/__init__.py
HastebinAPI-0.1.3.dist-info/LICENSE
HastebinAPI-0.1.3.dist-info/METADATA
HastebinAPI-0.1.3.dist-info/WHEEL
HastebinAPI-0.1.3.dist-info/top_level.txt
HastebinAPI-0.1.3.dist-info/RECORD
