Metadata-Version: 2.1
Name: HastebinAPI
Version: 0.1.3
Summary: A simple-to-use Hastebin API wrapper for Python.
Author-email: Alternate <alternated@mooncorerbx.com>
Project-URL: Homepage, https://google.com/
Project-URL: Bug Tracker, https://google.com/
Classifier: Programming Language :: Python :: 3
Classifier: License :: OSI Approved :: MIT License
Classifier: Operating System :: OS Independent
Requires-Python: >=3.7
License-File: LICENSE
